SimpleAudioIndexer/__init__ (copy).py
SimpleAudioIndexer/__init__.py
SimpleAudioIndexer/__main__.py
SimpleAudioIndexer-1.0.0.dist-info/DESCRIPTION.rst
SimpleAudioIndexer-1.0.0.dist-info/LICENSE.txt
SimpleAudioIndexer-1.0.0.dist-info/METADATA
SimpleAudioIndexer-1.0.0.dist-info/RECORD
SimpleAudioIndexer-1.0.0.dist-info/WHEEL
SimpleAudioIndexer-1.0.0.dist-info/entry_points.txt
SimpleAudioIndexer-1.0.0.dist-info/metadata.json
SimpleAudioIndexer-1.0.0.dist-info/top_level.txt
