Metadata-Version: 2.0
Name: SimpleAudioIndexer
Version: 1.0.0
Summary: Indexes audio files and searches for words/phrases or matches regex patterns within them.
Home-page: https://github.com/aalireza/SimpleAudioIndexer
Author: Alireza Rafiei (aalireza)
Author-email: mail@rafiei.net
License: Apache v2.0
Download-URL: https://github.com/aalireza/SimpleAudioIndexer/tarball/1.0.0
Keywords: audio,indexing,search,ibm,watson,anagram,subsequence,supersequence,sequence,timestamp,cmu,sphinx,cpmsphinx,speech,speech recognition
Platform: UNKNOWN
Classifier: Development Status :: 5 - Production/Stable
Classifier: Intended Audience :: Developers
Classifier: Topic :: Internet :: WWW/HTTP :: Indexing/Search
Classifier: Topic :: Software Development :: Libraries :: Python Modules
Classifier: Topic :: Utilities
Classifier: License :: OSI Approved :: Apache Software License
Classifier: Operating System :: MacOS :: MacOS X
Classifier: Operating System :: POSIX
Classifier: Operating System :: Unix
Classifier: Programming Language :: Python :: 2.7
Classifier: Programming Language :: Python :: 3.3
Classifier: Programming Language :: Python :: 3.4
Classifier: Programming Language :: Python :: 3.5
Classifier: Programming Language :: Python :: 3.6
Requires-Dist: requests
